flowforgeai/__init__.py
flowforgeai/decorator.py
flowforgeai-0.1.0.dist-info/LICENSE
flowforgeai-0.1.0.dist-info/METADATA
flowforgeai-0.1.0.dist-info/WHEEL
flowforgeai-0.1.0.dist-info/RECORD
