Metadata-Version: 2.1
Name: flowforgeai
Version: 0.1.0
Summary: "FlowForge" is designed to offer an intuitive interface that simplifies the process of creating and managing LLM workflows as a self-hosted solution.
License: MIT
Author: Tobias Sterbak
Author-email: github@tobiassterbak.com
Requires-Python: >=3.11,<4.0
Classifier: License :: OSI Approved :: MIT License
Classifier: Programming Language :: Python :: 3
Classifier: Programming Language :: Python :: 3.11
Requires-Dist: loguru (>=0.7.2,<0.8.0)
